clowder/__init__.py
clowder/clowder_app.py
clowder/clowder_controller.py
clowder/clowder_repo.py
clowder/cli/__init__.py
clowder/cli/base_controller.py
clowder/cli/branch_controller.py
clowder/cli/checkout_controller.py
clowder/cli/clean_controller.py
clowder/cli/diff_controller.py
clowder/cli/forall_controller.py
clowder/cli/herd_controller.py
clowder/cli/init_controller.py
clowder/cli/link_controller.py
clowder/cli/prune_controller.py
clowder/cli/repo_controller.py
clowder/cli/reset_controller.py
clowder/cli/save_controller.py
clowder/cli/start_controller.py
clowder/cli/stash_controller.py
clowder/cli/status_controller.py
clowder/cli/sync_controller.py
clowder/cli/yaml_controller.py
clowder/error/__init__.py
clowder/error/clowder_error.py
clowder/error/clowder_exit.py
clowder/error/clowder_git_error.py
clowder/error/clowder_yaml_error.py
clowder/git/__init__.py
clowder/git/project_repo.py
clowder/git/project_repo_impl.py
clowder/git/project_repo_recursive.py
clowder/git/repo.py
clowder/git/util.py
clowder/model/__init__.py
clowder/model/defaults.py
clowder/model/fork.py
clowder/model/group.py
clowder/model/project.py
clowder/model/source.py
clowder/util/__init__.py
clowder/util/clowder_utils.py
clowder/util/connectivity.py
clowder/util/decorators.py
clowder/util/execute.py
clowder/util/file_system.py
clowder/util/formatting.py
clowder/util/parallel_commands.py
clowder/util/progress.py
clowder/yaml/__init__.py
clowder/yaml/loading.py
clowder/yaml/parsing.py
clowder/yaml/printing.py
clowder/yaml/saving.py
clowder/yaml/validating.py
clowder/yaml/validation/__init__.py
clowder/yaml/validation/defaults.py
clowder/yaml/validation/forks.py
clowder/yaml/validation/groups.py
clowder/yaml/validation/projects.py
clowder/yaml/validation/sources.py
clowder/yaml/validation/util.py
clowder_repo-3.2.0.dist-info/METADATA
clowder_repo-3.2.0.dist-info/WHEEL
clowder_repo-3.2.0.dist-info/entry_points.txt
clowder_repo-3.2.0.dist-info/top_level.txt
clowder_repo-3.2.0.dist-info/RECORD
