Metadata-Version: 2.1
Name: clowder-repo
Version: 3.2.0
Summary: A tool for managing code
Home-page: http://clowder.cat
Author: Joe DeCapo
Author-email: joe@polka.cat
License: MIT
Platform: UNKNOWN
Classifier: Development Status :: 5 - Production/Stable
Classifier: Intended Audience :: Developers
Classifier: Topic :: Software Development :: Build Tools
Classifier: License :: OSI Approved :: MIT License
Classifier: Programming Language :: Python :: 3.6
Classifier: Programming Language :: Python :: 3.7
Requires-Dist: argcomplete
Requires-Dist: cement
Requires-Dist: colorama
Requires-Dist: GitPython
Requires-Dist: PyYAML
Requires-Dist: termcolor
Requires-Dist: psutil
Requires-Dist: tqdm
